hydra_plugins/hyper_analysis/README.md
hydra_plugins/hyper_analysis/__init__.py
hydra_plugins/hyper_analysis/ablation_path_sweeper.py
hydra_plugins/hyper_analysis/config.py
hydra_plugins/hyper_analysis/grid_sweeper.py
hydra_plugins/hyper_analysis/lpi_sweeper.py
hydra_plugins/hyper_analysis/utils.py
hydra_plugins/hyper_carp_s/__init__.py
hydra_plugins/hyper_carp_s/config.py
hydra_plugins/hyper_carp_s/hyper_carp_s.py
hydra_plugins/hyper_dehb/__init__.py
hydra_plugins/hyper_dehb/config.py
hydra_plugins/hyper_dehb/hyper_dehb.py
hydra_plugins/hyper_hebo/__init__.py
hydra_plugins/hyper_hebo/config.py
hydra_plugins/hyper_hebo/hyper_hebo.py
hydra_plugins/hyper_neps/__init__.py
hydra_plugins/hyper_neps/config.py
hydra_plugins/hyper_neps/hyper_neps.py
hydra_plugins/hyper_nevergrad/__init__.py
hydra_plugins/hyper_nevergrad/config.py
hydra_plugins/hyper_nevergrad/hyper_nevergrad.py
hydra_plugins/hyper_pbt/__init__.py
hydra_plugins/hyper_pbt/bg_pbt_utils.py
hydra_plugins/hyper_pbt/config.py
hydra_plugins/hyper_pbt/hyper_bg_pbt.py
hydra_plugins/hyper_pbt/hyper_pb2.py
hydra_plugins/hyper_pbt/hyper_pbt.py
hydra_plugins/hyper_pbt/pb2_utils.py
hydra_plugins/hyper_rs/__init__.py
hydra_plugins/hyper_rs/config.py
hydra_plugins/hyper_rs/hyper_rs.py
hydra_plugins/hyper_smac/__init__.py
hydra_plugins/hyper_smac/config.py
hydra_plugins/hyper_smac/hyper_smac.py
hydra_plugins/hypersweeper/__init__.py
hydra_plugins/hypersweeper/hypersweeper.code-workspace
hydra_plugins/hypersweeper/hypersweeper.py
hydra_plugins/hypersweeper/hypersweeper_backend.py
hydra_plugins/hypersweeper/hypersweeper_sweeper.py
hydra_plugins/hypersweeper/search_space_encoding.py
hydra_plugins/hypersweeper/utils.py
hypersweeper-0.2.3.dist-info/METADATA
hypersweeper-0.2.3.dist-info/WHEEL
hypersweeper-0.2.3.dist-info/licenses/AUTHORS.md
hypersweeper-0.2.3.dist-info/licenses/LICENSE
hypersweeper-0.2.3.dist-info/RECORD
