Metadata-Version: 2.4
Name: HyperSweeper
Version: 0.2.3
Summary: Hydra sweeper integration of our favorite optimization packages, utilizing ask-and-tell interfaces.
Author-email: AutoML Hannover <automl@ai.uni-hannover.de>
License: 
License-File: AUTHORS.md
License-File: LICENSE
Classifier: Intended Audience :: Developers
Classifier: Intended Audience :: Science/Research
Classifier: License :: OSI Approved :: BSD License
Classifier: Operating System :: POSIX
Classifier: Operating System :: Unix
Classifier: Programming Language :: Python
Classifier: Programming Language :: Python :: 3
Classifier: Topic :: Scientific/Engineering
Classifier: Topic :: Software Development
Requires-Python: >=3.10
Requires-Dist: bump-my-version
Requires-Dist: configspace~=1.2.0
Requires-Dist: coverage
Requires-Dist: hydra-colorlog
Requires-Dist: hydra-core~=1.3.2
Requires-Dist: hydra-submitit-launcher
Requires-Dist: matplotlib
Requires-Dist: mypy
Requires-Dist: numpy~=1.24.4
Requires-Dist: pandas~=2.1.0
Requires-Dist: pre-commit
Requires-Dist: pytest
Requires-Dist: ruff
Requires-Dist: smac~=2.1
Requires-Dist: tomli
Requires-Dist: twine~=5.1.1
Requires-Dist: typing-extensions
Requires-Dist: wandb==0.16.6
Provides-Extra: all
Requires-Dist: carps~=1.0.2; extra == 'all'
Requires-Dist: dehb==0.1.1; extra == 'all'
Requires-Dist: gpy~=1.13.2; extra == 'all'
Requires-Dist: hebo==0.3.5; extra == 'all'
Requires-Dist: nevergrad==1.0.2; extra == 'all'
Provides-Extra: carps
Requires-Dist: carps~=1.0.2; extra == 'carps'
Provides-Extra: dehb
Requires-Dist: dehb==0.1.1; extra == 'dehb'
Provides-Extra: dev
Requires-Dist: automl-sphinx-theme; extra == 'dev'
Requires-Dist: commitizen; extra == 'dev'
Requires-Dist: pluggy>=1.2.0; extra == 'dev'
Requires-Dist: pre-commit; extra == 'dev'
Requires-Dist: pytest; extra == 'dev'
Requires-Dist: pytest-cases; extra == 'dev'
Requires-Dist: pytest-coverage; extra == 'dev'
Requires-Dist: ruff; extra == 'dev'
Provides-Extra: doc
Requires-Dist: automl-sphinx-theme; extra == 'doc'
Provides-Extra: examples
Requires-Dist: deepcave; extra == 'examples'
Requires-Dist: scikit-learn; extra == 'examples'
Requires-Dist: stable-baselines3; extra == 'examples'
Provides-Extra: hebo
Requires-Dist: hebo==0.3.5; extra == 'hebo'
Provides-Extra: nevergrad
Requires-Dist: nevergrad==1.0.2; extra == 'nevergrad'
Provides-Extra: pbt
Requires-Dist: gpy~=1.13.2; extra == 'pbt'
Provides-Extra: test
Requires-Dist: pluggy>=1.2.0; extra == 'test'
Requires-Dist: pytest; extra == 'test'
Requires-Dist: pytest-cases; extra == 'test'
Requires-Dist: pytest-coverage; extra == 'test'
Provides-Extra: tooling
Requires-Dist: commitizen; extra == 'tooling'
Requires-Dist: pre-commit; extra == 'tooling'
Requires-Dist: ruff; extra == 'tooling'
